callder/__init__.py
callder/calculation.py
callder-0.1.2.dist-info/METADATA
callder-0.1.2.dist-info/WHEEL
callder-0.1.2.dist-info/top_level.txt
callder-0.1.2.dist-info/RECORD
